pyxlsb/__init__.py
pyxlsb/biff12.py
pyxlsb/handlers.py
pyxlsb/reader.py
pyxlsb/stringtable.py
pyxlsb/workbook.py
pyxlsb/worksheet.py
pyxlsb-1.0.7.dist-info/COPYING
pyxlsb-1.0.7.dist-info/COPYING.LESSER
pyxlsb-1.0.7.dist-info/METADATA
pyxlsb-1.0.7.dist-info/WHEEL
pyxlsb-1.0.7.dist-info/top_level.txt
pyxlsb-1.0.7.dist-info/RECORD
