Metadata-Version: 2.1
Name: pyxlsb
Version: 1.0.7
Summary: Excel 2007-2010 Binary Workbook (xlsb) parser
Home-page: https://github.com/willtrnr/pyxlsb
Author: William Turner
Author-email: willtur.will@gmail.com
License: LGPLv3+
Platform: UNKNOWN
Classifier: Development Status :: 5 - Production/Stable
Classifier: License :: OSI Approved :: GNU Lesser General Public License v3 or later (LGPLv3+)
Classifier: Programming Language :: Python :: 2
Classifier: Programming Language :: Python :: 2.7
Classifier: Programming Language :: Python :: 3
Classifier: Programming Language :: Python :: 3.5
Classifier: Programming Language :: Python :: 3.6
Classifier: Programming Language :: Python :: 3.7
Classifier: Programming Language :: Python :: 3.8
Classifier: Programming Language :: Python :: 3.9
